fustor_benchmark/__init__.py
fustor_benchmark/cli.py
fustor_benchmark/generator.py
fustor_benchmark/runner.py
fustor_benchmark/services.py
fustor_benchmark-0.2.16.dist-info/METADATA
fustor_benchmark-0.2.16.dist-info/WHEEL
fustor_benchmark-0.2.16.dist-info/entry_points.txt
fustor_benchmark-0.2.16.dist-info/top_level.txt
fustor_benchmark-0.2.16.dist-info/RECORD
