Metadata-Version: 2.4
Name: fustor-benchmark
Version: 0.2.16
Summary: Performance benchmarking tool for Fustor platform
Author-email: Huajin Wang <wanghuajin999@163.com>
Requires-Python: >=3.11
Requires-Dist: click>=8.1.7
Requires-Dist: requests>=2.31.0
Requires-Dist: pyyaml>=6.0.1
Requires-Dist: psutil>=5.9.0
